{
  "project_info": {
    "project_number": "491316445298",
    "firebase_url": "https://foodlauncher-84acb.firebaseio.com",
    "project_id": "foodlauncher-84acb",
    "storage_bucket": "foodlauncher-84acb.appspot.com"
  },
  "client": [
    {
      "client_info": {
        "mobilesdk_app_id": "1:491316445298:android:88716fbe9eb031a56fc2eb",
        "android_client_info": {
          "package_name": "com.launcher.foodlauncher"
        }
      },
      "oauth_client": [
        {
          "client_id": "491316445298-ipubie89cu352v14pvbgg08566igrecq.apps.googleusercontent.com",
          "client_type": 3
        }
      ],
      "api_key": [
        {
          "current_key": "AIzaSyCiFlIb6c-WDiE5phRXxL13eYS7ykDOTwg"
        }
      ],
      "services": {
        "appinvite_service": {
          "other_platform_oauth_client": [
            {
              "client_id": "491316445298-ipubie89cu352v14pvbgg08566igrecq.apps.googleusercontent.com",
              "client_type": 3
            }
          ]
        }
      }
    }
  ],
  "configuration_version": "1"
}